[{"chainId":"ethereum","dexId":"uniswap","url":"https://dexscreener.com/ethereum/0x99950bae3d0b79b8bee86a8a208ae1b087b9dcb0","pairAddress":"0x99950bAE3d0b79b8BeE86A8A208Ae1b087b9Dcb0","labels":["v3"],"baseToken":{"address":"0x50327c6c5a14DCaDE707ABad2E27eB517df87AB5","name":"TRON","symbol":"TRX"},"quoteToken":{"address":"0xC02aaA39b223FE8D0A0e5C4F27eAD9083C756Cc2","name":"Wrapped Ether","symbol":"WETH"},"priceNative":"0.00007699","priceUsd":"0.3437","txns":{"m5":{"buys":1,"sells":1},"h1":{"buys":14,"sells":12},"h6":{"buys":74,"sells":75},"h24":{"buys":254,"sells":281}},"volume":{"h24":13435429.79,"h6":3591227.95,"h1":836839.26,"m5":21915.56},"priceChange":{"m5":0.07,"h1":0.11,"h6":-0.36,"h24":-0.91},"liquidity":{"usd":43238981.65,"base":37168507,"quote":6822.7818},"fdv":102669574,"marketCap":24632912045,"pairCreatedAt":1734323279000,"info":{"imageUrl":"https://dd.dexscreener.com/ds-data/tokens/ethereum/0x50327c6c5a14dcade707abad2e27eb517df87ab5.png?key=3d5269","header":"https://dd.dexscreener.com/ds-data/tokens/ethereum/0x50327c6c5a14dcade707abad2e27eb517df87ab5/header.png?key=3d5269","openGraph":"https://cdn.dexscreener.com/token-images/og/ethereum/0x50327c6c5a14dcade707abad2e27eb517df87ab5?timestamp=1758450300000","websites":[{"label":"Website","url":"https://tron-tether.com/"}],"socials":[{"type":"twitter","url":"https://x.com/trondao"},{"type":"telegram","url":"https://telegram.me/tronnetworkEN"}]}}]